ciffile/__init__.py
ciffile/_helper.py
ciffile/creator.py
ciffile/exception.py
ciffile/reader.py
ciffile/typing.py
ciffile/parser/__init__.py
ciffile/parser/_exception.py
ciffile/parser/_output.py
ciffile/parser/_parser.py
ciffile/parser/_state.py
ciffile/parser/_token.py
ciffile/structure/__init__.py
ciffile/structure/_base.py
ciffile/structure/_block.py
ciffile/structure/_category.py
ciffile/structure/_file.py
ciffile/structure/_frame.py
ciffile/structure/_frames.py
ciffile/structure/_item.py
ciffile/structure/_util.py
ciffile/validation/__init__.py
ciffile/validation/_base.py
ciffile/validation/ddl2/__init__.py
ciffile/validation/ddl2/_caster.py
ciffile/validation/ddl2/_gen.py
ciffile/validation/ddl2/_input_schema.py
ciffile/validation/ddl2/_stringifier.py
ciffile/validation/ddl2/_validator.py
ciffile/writer/__init__.py
ciffile/writer/_category.py
ciffile-0.2.1.dist-info/METADATA
ciffile-0.2.1.dist-info/WHEEL
ciffile-0.2.1.dist-info/top_level.txt
ciffile-0.2.1.dist-info/RECORD
