Metadata-Version: 2.4
Name: CIFFile
Version: 0.2.1
Summary: A comprehensive Python library for reading, creating, processing, validating, and writing Crystallographic Information Files (CIF/mmCIF)
Author: scinformatic
License: MIT
Project-URL: Homepage, https://github.com/scinformatic/ciffile
Project-URL: Repository, https://github.com/scinformatic/ciffile
Project-URL: Documentation, https://github.com/scinformatic/ciffile/blob/main/README.md
Project-URL: Issues, https://github.com/scinformatic/ciffile/issues
Keywords: cif,mmcif,crystallography,pdb,pdbx,wwpdb,structure,bioinformatics
Classifier: Development Status :: 4 - Beta
Classifier: Intended Audience :: Science/Research
Classifier: Intended Audience :: Developers
Classifier: License :: OSI Approved :: MIT License
Classifier: Programming Language :: Python :: 3
Classifier: Programming Language :: Python :: 3.12
Classifier: Topic :: Scientific/Engineering :: Bio-Informatics
Classifier: Topic :: Scientific/Engineering :: Chemistry
Classifier: Topic :: Software Development :: Libraries :: Python Modules
Classifier: Typing :: Typed
Requires-Python: >=3.12
Requires-Dist: polars>=1
Requires-Dist: pydantic<3,>=2
Requires-Dist: FileEx<0.3,>=0.2.10
Requires-Dist: tqdm<5,>=4
